pdfless_api
